{
  "styles": {
    "label": {
      "promptLabel": {
        "name": "Pumpkin Power",
        "font": "Montserrat-Bold",
        "color": "#ffffff"
      },
      "Heading": {
        "name": "Naming the space",
        "font": "FSElliotPro-Heavy",
        "color": "#e3e0c585"
      },
      "textBold": {
        "name": "Bald Power",
        "font": "FSElliotPro-Heavy",
        "color": "#da3156"
      },
      "title": {
        "name": "Title",
        "font": "mcfont",
        "color": "#da3156"
      }
    }
  }
}