{
  "groups": {
    "mainFrame": {
      "panelOptions": {
        "opaque": false,
        "visible": true,
        "doubleBuffered": false,
        "background": "",
        "bounds": "0,0,850,500"
      },
      "childComponents": [
        {
          "readFrom": "assets/frames/forms/mainPanel/authForm.json"
        },
        {
          "readFrom": "assets/frames/forms/mainPanel/loggedForm.json"
        },
        {
          "readFrom": "assets/frames/forms/mainPanel/newsForm.json"
        },
        {
          "readFrom": "assets/frames/forms/mainPanel/settings.json"
        },
        {
          "readFrom": "assets/frames/forms/mainPanel/download.json"
        },
        {
          "readFrom": "assets/frames/forms/mainPanel/test.json"
        }
      ]
    }
  }
}