{
  "groups": {
    "generalSettings": {
      "panelOptions": {
        "opaque": true,
        "visible": true,
        "background": "#c0a1a0",
        "bounds": "10,60,320,240",
        "display": true
      },
      "childComponents": [
        {
          "componentType": "label",
          "fontSize": 16,
          "componentStyle": "Heading",
          "localeKey": "settings.baseOptions",
          "componentId": "baseOptions",
          "bounds": "5,-10,160,50"
        },
        {
          "componentType": "checkBox",
          "enabled": true,
          "componentStyle": "solid",
          "componentId": "autoEnter",
          "localeKey": "settings.autoEnter",
          "bounds": "5,20,240,32"
        },
        {
          "componentType": "checkBox",
          "enabled": true,
          "componentStyle": "solid",
          "componentId": "fullScreen",
          "localeKey": "settings.fullScreen",
          "bounds": "5,40,240,32"
        },
        {
          "componentType": "checkBox",
          "enabled": true,
          "componentStyle": "solid",
          "componentId": "loadNews",
          "localeKey": "settings.loadNews",
          "bounds": "5,60,240,32"
        },
        {
          "componentType": "checkBox",
          "enabled": true,
          "componentStyle": "solid",
          "componentId": "enableSound",
          "localeKey": "settings.enableSound",
          "bounds": "5,80,240,32"
        },
        {
          "componentType": "label",
          "fontSize": 12,
          "componentStyle": "promptLabel",
          "localeKey": "settings.ramField",
          "componentId": "ramField",
          "bounds": "10,90,250,50"
        },
        {
          "componentType": "textField",
          "componentStyle": "inputBox",
          "localeKey": "settings.ramPlaceholder",
          "componentId": "ramAmount",
          "bounds": "10,125,0,0"
        },
        {
          "componentType": "button",
          "componentStyle": "buttonGreen",
          "componentId": "applySettings",
          "localeKey": "settings.applySettings",
          "bounds": "60,195,160,34"
        }
      ]
    }
  }
}