{
  "button": {
    "click": {
      "sounds": [
        "assets/sounds/button/buttonClick.ogg"
      ]
    },
    "clickSmall": {
      "sounds": [
        "assets/sounds/button/buttonClickSmall.ogg"
      ]
    },
    "back": {
      "sounds": [
        "assets/sounds/button/buttonBack.ogg"
      ]
    },
    "hover": {
      "sounds": [
        "assets/sounds/button/buttonHover.ogg"
      ]
    },
    "close": {
      "sounds": [
        "assets/sounds/button/buttonClose.ogg"
      ]
    }
  },
  "checkbox": {
    "checkboxOn": {
      "sounds": [
        "assets/sounds/checkbox/on/checkboxOn.ogg",
        "assets/sounds/checkbox/on/checkboxOn1.ogg"
      ]
    },
    "checkboxOff": {
      "sounds": [
        "assets/sounds/checkbox/off/checkboxOff.ogg",
        "assets/sounds/checkbox/off/checkboxOff1.ogg"
      ]
    }
  },
  "dropBox": {
    "dropBoxOpen": {
      "sounds": [
        "assets/sounds/dropBox/dropBoxOpen.ogg"
      ]
    },
    "dropBoxClose": {
      "sounds": [
        "assets/sounds/dropBox/dropBoxClose.ogg"
      ]
    }
  },
  "music": {
    "inLauncher": {
      "sounds": [
        "assets/sounds/mus/loginMus.ogg"
      ]
    }
  },
  "other": {
    "loggedIn": {
      "sounds": [
        "assets/sounds/auth.ogg"
      ]
    },
    "test": {
      "sounds": [
        "assets/sounds/test/test0.ogg",
        "assets/sounds/test/test1.ogg",
        "assets/sounds/test/test2.ogg",
        "assets/sounds/test/test3.ogg",
        "assets/sounds/test/test4.ogg",
        "assets/sounds/test/test5.ogg",
        "assets/sounds/test/test6.ogg",
        "assets/sounds/test/test7.ogg",
        "assets/sounds/test/test8.ogg"
      ]
    }
  }
}
