{
  "config": {
    "fps": 732,
    "loop":false,
    "hardwareAccelerationEnabled": true,
    "scale": 1.0,
    "totalFrames": 5000,
    "width": 720,
    "height": 350
  },
  "layers": [
    {
      "type": "image",
      "name": "Background",
      "shape": "image",
      "color": "#FFFFFF",
      "imagePath": "",
      "keyframes": [
        { "time": 2000,
          "effect": {
            "type": "ExampleRenderEffect",
            "parameters": {
              "tint": "#d59615",
              "intensity": 0.8,
              "duration": 3000,
              "borderRadius": 35
            }
          }}
      ]
    },
    {
      "type": "image",
      "name": "AidenFox",
      "shape": "image",
      "color": "#FFFFFF",
      "imagePath": "brand/aidenfox.png",
      "particles": {
        "particle": "heart",
        "lifetime":  90,
        "fadeDuration": 30,
        "spacing": 128,
        "scale": 0.35,
        "count": 3
      },
      "keyframes": [
        {"time":  0, "soundFile":  "intro.ogg", "volume":  0.5},
        { "time": 1000, "position": { "x": -500, "y": 150 }, "radius": 1, "rotation": 0, "opacity": 0.6, "scaleX": 1, "scaleY": 1 },
        { "time": 2000, "position": { "x": 200, "y": 150 }, "radius": 1, "rotation": 0, "opacity": 0.7, "scaleX": 1, "scaleY": 1 },
        { "time": 3000, "position": { "x": 200, "y": 150 }, "radius": 1, "rotation": 0, "opacity": 0.8, "scaleX": 1, "scaleY": 1 },
        { "time": 5000, "position": { "x": 200, "y": 150 }, "radius": 1, "rotation": 0, "opacity": 1, "scaleX": 1, "scaleY": 1}
      ]
    },
    {
      "type": "image",
      "name": "Logo",
      "shape": "image",
      "color": "#FFFFFF",
      "imagePath": "brand/logo.png",
      "particles": {
        "particle": "smoke",
        "lifetime":  140,
        "fadeDuration": 20,
        "spacing": 128.0,
        "scale": 0.5,
        "count": 10
      },
      "keyframes": [
        { "time": 3000, "position": { "x": 480, "y": -1000 }, "radius": 1, "rotation": 0, "opacity": 1, "scaleX": 1, "scaleY": 0.1, "soundFile": "whoosh.ogg", "volume":  0.3 },
        { "time": 5000, "position": { "x": 480, "y": 50 },    "radius": 1, "rotation": 0, "opacity": 1, "scaleX": 1, "scaleY": 0.1 },
        { "time": 8000, "position": { "x": 480, "y": 50 },    "radius": 0.5, "rotation": 0, "opacity": 1, "scaleX": 1, "scaleY": 1 },
        { "time": 10000, "position": { "x": 480, "y": 50 },    "radius": 1, "rotation": 0, "opacity": 1, "scaleX": 1, "scaleY": 1 }
      ]
    },
    {
      "type": "image",
      "name": "Alt Text",
      "shape": "image",
      "color": "#FFFFFF",
      "imagePath": "brand/alt.png",
      "particles": {
        "particle": "goldentrail",
        "lifetime":  30,
        "fadeDuration": 12,
        "spacing": 128.0,
        "scale": 0.3,
        "count": 10
      },
      "keyframes": [
        { "time": 4800, "position": { "x": 480, "y": 1000 }, "radius": 1, "rotation": 0, "opacity": 1, "scaleX": 0.1, "scaleY": 1, "soundFile": "whoosh.ogg", "volume":  0.2},
        { "time": 8000, "position": { "x": 480, "y": 80 }, "radius": 1, "rotation": 0, "opacity": 1, "scaleX": 0.3, "scaleY": 1 },
        { "time": 10000, "position": { "x": 480, "y": 80 }, "radius": 1, "rotation": 360, "opacity": 1, "scaleX": 1, "scaleY": 1 },
        { "time": 12000, "position": { "x": 460, "y": 85 }, "radius": 0.9, "rotation": 360, "opacity": 1, "scaleX": 1, "scaleY": 1 }
      ]
    },
    {
      "type": "image",
      "name": "Stone",
      "shape": "image",
      "color": "#FFFFFF",
      "imagePath": "brand/robotnik.png",
      "particles": {
        "particle": "goldentrail",
        "lifetime":  90,
        "fadeDuration": 12,
        "spacing": 128.0,
        "scale": 0.5,
        "count": 10
      },
      "keyframes": [
        { "time": 10000, "position": { "x": 500, "y": 100 }, "radius": 1.00, "rotation": 0, "opacity": 0, "scaleX": 1, "scaleY": 1 , "soundFile":  "ha.ogg", "volume":  1.0},
        { "time": 11000, "position": { "x": 430, "y": 125 }, "radius": 0.50, "rotation": 360, "opacity": 1, "scaleX": 1, "scaleY": 1 },
        { "time": 11300, "position": { "x": 430, "y": 125 }, "radius": 0.28, "rotation": 360, "opacity": 1, "scaleX": 1, "scaleY": 1 },
        { "time": 12600, "position": { "x": 430, "y": 125 }, "radius": 0.18, "rotation": 360, "opacity": 1, "scaleX": 1, "scaleY": 1 },
        { "time": 12900, "position": { "x": 430, "y": 125 }, "radius": 0.14, "rotation": 360, "opacity": 1, "scaleX": 1, "scaleY": 1 },
        { "time": 13200, "position": { "x": 430, "y": 125 }, "radius": 0.12, "rotation": 360, "opacity": 1, "scaleX": 1, "scaleY": 1 },
        { "time": 13500, "position": { "x": 430, "y": 125 }, "radius": 0.15, "rotation": 360, "opacity": 1, "scaleX": 1, "scaleY": 1}
      ]
    },
    {
      "type": "text",
      "name": "authority",
      "shape": "text",
      "textColor": "#ac6343",
      "fontName": "Sans Serif",
      "text": "By FoxesWorld",
      "keyframes": [
        { "time": 1000, "position": { "x": 8000, "y": 175 }, "opacity": 1, "scaleX": 1, "scaleY": 1},
        { "time": 11000, "position": { "x": 1000, "y": 175 }, "opacity": 0.1, "scaleX": 1, "scaleY": 1,  "soundFile":  "whoosh1.ogg", "volume":  1.0},
        { "time": 12000, "position": { "x": 460, "y": 175 }, "opacity": 1, "scaleX": 1, "scaleY": 1}
      ]
    }
  ]
}
